sessionlib/__init__.py
sessionlib/sessionlib.py
sessionlib/utils.py
sessionlib-0.2.1.dist-info/DESCRIPTION.rst
sessionlib-0.2.1.dist-info/METADATA
sessionlib-0.2.1.dist-info/RECORD
sessionlib-0.2.1.dist-info/WHEEL
sessionlib-0.2.1.dist-info/metadata.json
sessionlib-0.2.1.dist-info/top_level.txt
