Metadata-Version: 2.0
Name: sessionlib
Version: 0.2.1
Summary: Session Library
Home-page: https://github.com/pauloromeira/sessionlib
Author: Paulo Romeira
Author-email: paulo@pauloromeira.com
License: MIT license
Download-URL: https://github.com/pauloromeira/sessionlib/tarball/0.2.1
Keywords: sessionlib
Platform: UNKNOWN
Classifier: Development Status :: 2 - Pre-Alpha
Classifier: Intended Audience :: Developers
Classifier: License :: OSI Approved :: MIT License
Classifier: Natural Language :: English
Classifier: Programming Language :: Python :: 3
Classifier: Programming Language :: Python :: 3.3
Classifier: Programming Language :: Python :: 3.4
Classifier: Programming Language :: Python :: 3.6
